adamr/__init__.py
adamr/adamr.py
adamr-0.0.2.dist-info/METADATA
adamr-0.0.2.dist-info/WHEEL
adamr-0.0.2.dist-info/licenses/LICENSE
adamr-0.0.2.dist-info/RECORD
