Metadata-Version: 2.1
Name: adamr
Version: 0.0.2
Summary: Adam with weight recovery optimizer for pytorch
Project-URL: Homepage, https://github.com/TYTTYTTYT/AdamR
Project-URL: Bug Tracker, https://github.com/TYTTYTTYT/AdamR/issues
Project-URL: repository, https://github.com/TYTTYTTYT/AdamR.git
Author-email: Yintao Tai <tai.yintao@gmail.com>
License-File: LICENSE
Classifier: Development Status :: 4 - Beta
Classifier: License :: OSI Approved :: Apache Software License
Classifier: Operating System :: OS Independent
Classifier: Programming Language :: Python :: 3
Classifier: Topic :: Scientific/Engineering :: Artificial Intelligence
Classifier: Topic :: Scientific/Engineering :: Mathematics
Requires-Python: >=3.10
